aiobitcoin/__init__.py
aiobitcoin/bitcoinerrors.py
aiobitcoin/bitcointools.py
aiobitcoin/blockchain.py
aiobitcoin/encoding.py
aiobitcoin/grambitcoin.py
aiobitcoin/grambitcoincommon.py
aiobitcoin/mnemonic.py
aiobitcoin/network.py
aiobitcoin/util.py
aiobitcoin/wallet.py
aiobitcoin/config/__init__.py
aiobitcoin/config/config.py
aiobitcoin/config/opcodes.py
aiobitcoin/config/secp256k1.py
aiobitcoin/tools/__init__.py
aiobitcoin/tools/base58.py
aiobitcoin/tools/bip32.py
aiobitcoin/tools/block.py
aiobitcoin/tools/curve.py
aiobitcoin/tools/curves.py
aiobitcoin/tools/encoding.py
aiobitcoin/tools/intbytes.py
aiobitcoin/tools/merkle.py
aiobitcoin/tools/numbertheory.py
aiobitcoin/tools/utils.py
aiobitcoin/tools/contrib/__init__.py
aiobitcoin/tools/contrib/segwit_addr.py
aiobitcoin/tools/convention/__init__.py
aiobitcoin/tools/ecdsa/__init__.py
aiobitcoin/tools/ecdsa/ecdsa.py
aiobitcoin/tools/ecdsa/ellipticcurve.py
aiobitcoin/tools/ecdsa/intstream.py
aiobitcoin/tools/ecdsa/numbertheory.py
aiobitcoin/tools/ecdsa/rfc6979.py
aiobitcoin/tools/ecdsa/secp256k1.py
aiobitcoin/tools/ecdsa/native/__init__.py
aiobitcoin/tools/ecdsa/native/bignum.py
aiobitcoin/tools/ecdsa/native/library.py
aiobitcoin/tools/key/BIP32Node.py
aiobitcoin/tools/key/Key.py
aiobitcoin/tools/key/__init__.py
aiobitcoin/tools/key/bip32.py
aiobitcoin/tools/key/validate.py
aiobitcoin/tools/networks/__init__.py
aiobitcoin/tools/networks/all.py
aiobitcoin/tools/networks/default.py
aiobitcoin/tools/networks/legacy_networks.py
aiobitcoin/tools/networks/network.py
aiobitcoin/tools/networks/registry.py
aiobitcoin/tools/serialize/__init__.py
aiobitcoin/tools/serialize/bitcoin_streamer.py
aiobitcoin/tools/serialize/streamer.py
aiobitcoin/tools/tx/Spendable.py
aiobitcoin/tools/tx/Tx.py
aiobitcoin/tools/tx/TxIn.py
aiobitcoin/tools/tx/TxOut.py
aiobitcoin/tools/tx/__init__.py
aiobitcoin/tools/tx/exceptions.py
aiobitcoin/tools/tx/pay_to/ScriptMultisig.py
aiobitcoin/tools/tx/pay_to/ScriptNulldata.py
aiobitcoin-0.75.14.dist-info/LICENSE
aiobitcoin-0.75.14.dist-info/METADATA
aiobitcoin-0.75.14.dist-info/WHEEL
aiobitcoin-0.75.14.dist-info/top_level.txt
aiobitcoin-0.75.14.dist-info/RECORD
