Metadata-Version: 2.1
Name: aiobitcoin
Version: 0.75.14
Summary: Bitcoin lib for working with Bitcoin RPC.
Home-page: https://github.com/mkbeh/aiobitcoin
Author: mkbeh
Author-email: mkbehforever@gmail.com
License: MIT
Platform: UNKNOWN
Requires-Dist: aiohttp (==3.5.4)
Requires-Dist: async-timeout (==3.0.1)
Requires-Dist: attrs (==19.1.0)
Requires-Dist: chardet (==3.0.4)
Requires-Dist: idna (==2.8)
Requires-Dist: idna-ssl (==1.1.0)
Requires-Dist: multidict (==4.5.2)
Requires-Dist: typing-extensions (==3.7.2)
Requires-Dist: ujson (==1.35)
Requires-Dist: yarl (==1.3.0)
